{
  "currentRound": "R2",
  "lastUpdated": "15:02 BST",
  "source": "ESPN HTML",
  "players": {
    "Xander Schauffele": {
      "position": 7,
      "cut": false,
      "live": false,
      "toPar": "-2",
      "r1": "70",
      "r2": "--",
      "r3": "--",
      "r4": "--"
    },
    "Tommy Fleetwood": {
      "position": 12,
      "cut": false,
      "live": false,
      "toPar": "-1",
      "r1": "71",
      "r2": "--",
      "r3": "--",
      "r4": "--"
    },
    "Harris English": {
      "position": 27,
      "cut": false,
      "live": false,
      "toPar": "+1",
      "r1": "73",
      "r2": "--",
      "r3": "--",
      "r4": "--"
    },
    "Charl Schwartzel": {
      "position": 47,
      "cut": false,
      "live": false,
      "toPar": "+3",
      "r1": "75",
      "r2": "--",
      "r3": "--",
      "r4": "--"
    },
    "Jon Rahm": {
      "position": 7,
      "cut": false,
      "live": false,
      "toPar": "+6",
      "r1": "78",
      "r2": "--",
      "r3": "--",
      "r4": "--"
    },
    "Tyrrell Hatton": {
      "position": 1,
      "cut": false,
      "live": false,
      "toPar": "+2",
      "r1": "74",
      "r2": "--",
      "r3": "--",
      "r4": "--"
    },
    "Cameron Smith": {
      "position": 39,
      "cut": false,
      "live": false,
      "toPar": "+2",
      "r1": "74",
      "r2": "--",
      "r3": "--",
      "r4": "--"
    },
    "Dustin Johnson": {
      "position": 27,
      "cut": false,
      "live": false,
      "toPar": "+1",
      "r1": "73",
      "r2": "--",
      "r3": "--",
      "r4": "--"
    },
    "Matt Fitzpatrick": {
      "position": 39,
      "cut": false,
      "live": false,
      "toPar": "+2",
      "r1": "74",
      "r2": "--",
      "r3": "--",
      "r4": "--"
    },
    "JJ Spaun": {
      "position": 1,
      "cut": false,
      "live": false,
      "toPar": "+2",
      "r1": "74",
      "r2": "--",
      "r3": "--",
      "r4": "--"
    },
    "Aaron Rai": {
      "position": 3,
      "cut": false,
      "live": false,
      "toPar": "-2",
      "r1": "71",
      "r2": "--",
      "r3": "--",
      "r4": "--"
    },
    "Cameron Young": {
      "position": 27,
      "cut": false,
      "live": false,
      "toPar": "+1",
      "r1": "73",
      "r2": "--",
      "r3": "--",
      "r4": "--"
    },
    "Marco Penge": {
      "position": 52,
      "cut": false,
      "live": false,
      "toPar": "+4",
      "r1": "76",
      "r2": "--",
      "r3": "--",
      "r4": "--"
    },
    "Samuel Stevens": {
      "position": 22,
      "cut": false,
      "live": false,
      "toPar": "+2",
      "r1": "72",
      "r2": "--",
      "r3": "--",
      "r4": "--"
    },
    "Bryson DeChambeau": {
      "position": 52,
      "cut": false,
      "live": false,
      "toPar": "+4",
      "r1": "76",
      "r2": "--",
      "r3": "--",
      "r4": "--"
    },
    "Chris Gotterup": {
      "position": 10,
      "cut": false,
      "live": false,
      "toPar": "+1",
      "r1": "72",
      "r2": "--",
      "r3": "--",
      "r4": "--"
    },
    "Sergio Garcia": {
      "position": 10,
      "cut": false,
      "live": false,
      "toPar": "+1",
      "r1": "72",
      "r2": "--",
      "r3": "--",
      "r4": "--"
    }
  }
}